<annotation>
	<folder>my-project-name</folder>
	<filename>20074.jpg</filename>
	<path>/my-project-name/20074.jpg</path>
	<source>
		<database>Unspecified</database>
	</source>
	<size>
		<width>4624</width>
		<height>3468</height>
		<depth>3</depth>
	</size>
	<object>
		<name>semi_open</name>
		<pose>Unspecified</pose>
		<truncated>0</truncated>
		<difficult>0</difficult>
		<bndbox>
			<xmin>748</xmin>
			<ymin>1053</ymin>
			<xmax>2110</xmax>
			<ymax>2791</ymax>
		</bndbox>
	</object>
	<object>
		<name>semi_open</name>
		<pose>Unspecified</pose>
		<truncated>0</truncated>
		<difficult>0</difficult>
		<bndbox>
			<xmin>3307</xmin>
			<ymin>892</ymin>
			<xmax>4624</xmax>
			<ymax>2935</ymax>
		</bndbox>
	</object>
</annotation>