<annotation>
	<folder>my-project-name</folder>
	<filename>20276.jpg</filename>
	<path>/my-project-name/20276.jpg</path>
	<source>
		<database>Unspecified</database>
	</source>
	<size>
		<width>4624</width>
		<height>3468</height>
		<depth>3</depth>
	</size>
	<object>
		<name>fully_open</name>
		<pose>Unspecified</pose>
		<truncated>0</truncated>
		<difficult>0</difficult>
		<bndbox>
			<xmin>1107</xmin>
			<ymin>977</ymin>
			<xmax>2196</xmax>
			<ymax>2545</ymax>
		</bndbox>
	</object>
	<object>
		<name>semi_open</name>
		<pose>Unspecified</pose>
		<truncated>0</truncated>
		<difficult>0</difficult>
		<bndbox>
			<xmin>2236</xmin>
			<ymin>798</ymin>
			<xmax>4167</xmax>
			<ymax>2536</ymax>
		</bndbox>
	</object>
</annotation>