<annotation>
	<folder>my-project-name</folder>
	<filename>20623.jpg</filename>
	<path>/my-project-name/20623.jpg</path>
	<source>
		<database>Unspecified</database>
	</source>
	<size>
		<width>719</width>
		<height>1600</height>
		<depth>3</depth>
	</size>
	<object>
		<name>semi_open</name>
		<pose>Unspecified</pose>
		<truncated>0</truncated>
		<difficult>0</difficult>
		<bndbox>
			<xmin>78</xmin>
			<ymin>365</ymin>
			<xmax>717</xmax>
			<ymax>1004</ymax>
		</bndbox>
	</object>
</annotation>